{
  "buildx.build.provenance": {
    "buildType": "https://mobyproject.org/buildkit@v1",
    "materials": [
      {
        "uri": "pkg:docker/kubeovn/kube-ovn-base@v1.12.19?platform=linux%2Famd64",
        "digest": {
          "sha256": "9f9e2199be2a0a10d058c3f45bda08d3a3ea9a8817170219a8f898c90ffbdf9e"
        }
      },
      {
        "uri": "pkg:docker/golang@1.22-bookworm?platform=linux%2Famd64",
        "digest": {
          "sha256": "39b7e6ebaca464d51989858871f792f2e186dce8ce0cbdba7e88e4444b244407"
        }
      }
    ],
    "invocation": {
      "configSource": {
        "entryPoint": "Dockerfile"
      },
      "parameters": {
        "frontend": "dockerfile.v0",
        "locals": [
          {
            "name": "context"
          },
          {
            "name": "dockerfile"
          }
        ]
      },
      "environment": {
        "platform": "linux/amd64"
      }
    }
  },
  "buildx.build.ref": "buildkit/buildkit0/m5gbswwgqddc64uba1uy011fy",
  "containerimage.config.digest": "sha256:050f4b7fe5e8812106c70cc8865b109258f55e9d32f5ab92f1a76347ff620144",
  "containerimage.descriptor": {
    "mediaType": "application/vnd.docker.distribution.manifest.v2+json",
    "digest": "sha256:af48ff43d05006403f2dbc072a98a1b167a4ddd7ba6d90a7063c9a30401f4bc5",
    "size": 5015,
    "platform": {
      "architecture": "amd64",
      "os": "linux"
    }
  },
  "containerimage.digest": "sha256:af48ff43d05006403f2dbc072a98a1b167a4ddd7ba6d90a7063c9a30401f4bc5",
  "image.name": "ghcr.io/aenix-io/cozystack/kubeovn:v1.13.0,ghcr.io/aenix-io/cozystack/kubeovn:v1.13.0-v0.10.4"
}